nanoPDB-0.1.0.dist-info/METADATA
nanoPDB-0.1.0.dist-info/WHEEL
nanoPDB/__init__.py
nanoPDB/__init__.pyi
nanoPDB/py.typed
nanoPDB/nanoPDB.cp311-win_amd64.pyd
nanoPDB-0.1.0.dist-info/RECORD
